neatly/__init__.py
neatly/classes.py
neatly/functions.py
neatly/helpers.py
neatly/lazy.py
neatly-0.0.21.3.dist-info/LICENSE
neatly-0.0.21.3.dist-info/METADATA
neatly-0.0.21.3.dist-info/WHEEL
neatly-0.0.21.3.dist-info/top_level.txt
neatly-0.0.21.3.dist-info/RECORD
