Metadata-Version: 2.1
Name: neatly
Version: 0.0.21.3
Summary: A NEAT package
Home-page: https://github.com/s2011r2593/neatly
Author: Sean Rhee
Author-email: seanrhee2024@u.northwestern.edu
License: UNKNOWN
Platform: UNKNOWN
Classifier: Programming Language :: Python :: 3
Classifier: License :: OSI Approved :: MIT License
Classifier: Operating System :: OS Independent
Requires-Python: >=3.8
